setup.cfg
setup.py
parsines/__init__.py
parsines/__main__.py
parsines/cli.py
parsines/parser.py
parsines/reporters.py
parsines.egg-info/PKG-INFO
parsines.egg-info/SOURCES.txt
parsines.egg-info/dependency_links.txt
parsines.egg-info/entry_points.txt
parsines.egg-info/top_level.txt