Metadata-Version: 1.1
Name: parsines
Version: 1.0.0a2
Summary: A library for reading iNES formatted NES ROM files.
Home-page: https://www.github.com/wkmanire/parsines
Author: wkmanire
Author-email: williamkmanire@gmail.com
License: GPLv3
Keywords: nes emulation ines rom
Platform: UNKNOWN
Classifier: Development Status :: 3 - Alpha
Classifier: Intended Audience :: Developers
Classifier: Topic :: System :: Emulators
Classifier: Topic :: Utilities
Classifier: License :: OSI Approved :: GNU General Public License v3 (GPLv3)
Classifier: Programming Language :: Python :: 2.7
Classifier: Programming Language :: Python :: 3.4
